sinyi_utils/__init__.py
sinyi_utils/db_connector.py
sinyi_utils/format_tool.py
sinyi_datateam_utils-0.2.0.dist-info/METADATA
sinyi_datateam_utils-0.2.0.dist-info/WHEEL
sinyi_datateam_utils-0.2.0.dist-info/top_level.txt
sinyi_datateam_utils-0.2.0.dist-info/RECORD
