Metadata-Version: 2.1
Name: sinyi-datateam-utils
Version: 0.2.0
Summary: Utilities for data analysis
Home-page: https://SinyiDataTeam@dev.azure.com/SinyiDataTeam/Label360/_git/sinyi_utils
Author: sinyidatateam
Author-email: me30@sinyi.com.tw
License: MIT
Requires-Python: >=3.8
Requires-Dist: pycryptodome
Requires-Dist: pandas-gbq
Requires-Dist: google-cloud-storage
Requires-Dist: azure-identity
Requires-Dist: azure-keyvault-secrets
